Metadata-Version: 2.1
Name: odoo11-addon-stock-picking-mass-action
Version: 11.0.1.1.0.99.dev12
Summary: Stock Picking Mass Action
Home-page: https://github.com/OCA/stock-logistics-workflow/
Author: Camptocamp, GRAP,Tecnativa,Odoo Community Association (OCA)
Author-email: support@odoo-community.org
License: AGPL-3
Platform: UNKNOWN
Classifier: Programming Language :: Python
Classifier: Framework :: Odoo
Classifier: Framework :: Odoo :: 11.0
Classifier: License :: OSI Approved :: GNU Affero General Public License v3
Requires-Python: >=2.7, !=3.0.*, !=3.1.*, !=3.2.*, !=3.3.*, !=3.4.*
Requires-Dist: odoo <11.1dev,>=11.0a
